{
  "categories": {
    "items": [
      {
        "id": 1,
        "level": 1,
        "name": "ผัก",
        "children": [
            {
                "level": 2,
                "name":"ผักใบ"
            },
            {
                "level": 2,
                "name":"ผักหัว"
            },
            {
                "level": 2,
                "name":"ราก"
            },
            {
                "level": 2,
                "name":"เห็ด"
            },
            {
                "level": 2,
                "name":"ชุดผักรวม"
            },
            {
                "level": 2,
                "name":"ผักออร์แกนิค"
            },
            {
                "level": 2,
                "name":"ผักพื้นบ้าน"
            },
            {
                "level": 2,
                "name":"ผักนำเข้า"
            },
            {
                "level": 2,
                "name":"ผักสลัด"
            }
            
        ]
      },
      {
        "id": 2,
        "level": 1,
        "name": "ผลไม้",
        "children": [
            {
                "level": 2,
                "name":"ผลไม้ไทย"
            },
            {
                "level": 2,
                "name":"ผลไม้นำเข้า"
            },
            {
                "level": 2,
                "name":"ผลไม้ตัดแต่ง"
            }
            
            
        ]
      },
      {
        "id": 3,
        "level": 1,
        "name": "เนื้อสัตว์",
        "children": [
            {
                "level": 2,
                "name":"เนื้อหมู"
            },
            {
                "level": 2,
                "name":"เนื้อไก่และสัตว์ปีก"
            },
            {
                "level": 2,
                "name":"เนื้อวัว"
            },
            {
                "level": 2,
                "name":"เนื้อแกะ"
            },
            {
                "level": 2,
                "name":"เนื้อ อื่น ๆ"
            }
            
            
        ]
      },
      {
        "id": 4,
        "level": 1,
        "name": "อาหารทะเล",
        "children": [
            {
                "level": 2,
                "name":"กุ้ง"
            },
            {
                "level": 2,
                "name":"หอย"
            },
            {
                "level": 2,
                "name":"ปู"
            },
            {
                "level": 2,
                "name":"ปลา"
            },
            {
                "level": 2,
                "name":"ปลาหมึก"
            },
            {
                "level": 2,
                "name":"อาหารทะเลแช่แข็ง"
            }
            
            
        ]
      },
      {
        "id": 5,
        "level": 1,
        "name": "อาหารแห้ง",
        "children": [
            {
                "level": 2,
                "name":"ข้าวสาร"
            },
            {
                "level": 2,
                "name":"ส่วนผสมและเครื่องปรุง"
            },
            {
                "level": 2,
                "name":"แป้งทำอาหาร แป้งทำขนม"
            },
            {
                "level": 2,
                "name":"เส้นก๋วยเตี๋ยว และพาสต้า"
            },
            {
                "level": 2,
                "name":"ถั่วและธัญพืช"
            },
            {
                "level": 2,
                "name":"ผักและผลไม้ อบหรือตากแห้ง"
            },
            {
                "level": 2,
                "name":"เนื้อสัตว์อบหรือตากแห้ง"
            },
            {
                "level": 2,
                "name":"อาหารกึ่งสำเร็จรูป"
            }
            
            
        ]
      },
      {
        "id": 6,
        "level": 1,
        "name": "ผลิตภัณฑ์แปรรูป",
        "children": [
            {
                "level": 2,
                "name":"ลูกชิ้น"
            },
            {
                "level": 2,
                "name":"แฮม"
            },
            {
                "level": 2,
                "name":"ใส้กรอก"
            },
            {
                "level": 2,
                "name":"เบคอน"
            },
            {
                "level": 2,
                "name":"แหนม"
            },
            {
                "level": 2,
                "name":"ยอ"
            },
            {
                "level": 2,
                "name":"เต้าหู้"
            },
            {
                "level": 2,
                "name":"อาหารกระป๋อง"
            },
            {
                "level": 2,
                "name":"หยอง"
            },
            {
                "level": 2,
                "name":"เชียง"
            },
            {
                "level": 2,
                "name":"ไส้อั่ว"
            }
            
            
        ]
      },
      {
        "id": 7,
        "level": 1,
        "name": "อาหารพร้อมทาน",
        "children": [
            {
                "level": 2,
                "name":"อาหารพร้อมทานแช่เย็น"
            },
            {
                "level": 2,
                "name":"อาหารพร้อมทานแช่แข็ง"
            },
            {
                "level": 2,
                "name":"อาหารพร้อมปรุง"
            }
            
        ]
      },
      {
        "id": 8,
        "level": 1,
        "name": "อาหารเพื่อสุขภาพ",
        "children": [
            {
                "level": 2,
                "name":"โปรตีน"
            },
            {
                "level": 2,
                "name":"ไขมันต่ำ"
            },
            {
                "level": 2,
                "name":"โซเดียมต่ำ"
            },
            {
                "level": 2,
                "name":"แคลอรี่ต่ำ"
            },
            {
                "level": 2,
                "name":"คีโต"
            },
            {
                "level": 2,
                "name":"สลัด"
            },
            {
                "level": 2,
                "name":"มังสวิรัติ/เจ"
            }

        ]
      },
      {
        "id": 9,
        "level": 1,
        "name": "ขนม/ไอศกรีม",
        "children": [
            {
                "level": 2,
                "name":"มันฝรั่งทอด"
            },
            {
                "level": 2,
                "name":"ขนมอบกรอบ"
            },
            {
                "level": 2,
                "name":"ช็อกโกแลต"
            },
            {
                "level": 2,
                "name":"ลูกอม/เจลลี่/หมากฝรั่ง"
            },
            {
                "level": 2,
                "name":"คุกกี้/บิสกิต/แครกเกอร์"
            },
            {
                "level": 2,
                "name":"ถั่ว/ผลไม้อบแห้ง"
            },
            {
                "level": 2,
                "name":"สาหร่าย"
            },
            {
                "level": 2,
                "name":"ไอศกรีมถ้วย"
            },
            {
                "level": 2,
                "name":"ไอศกรีมแท่ง"
            }

        ]
      },
      {
        "id": 10,
        "level": 1,
        "name": "เบเกอรี่",
        "children": [
            {
                "level": 2,
                "name":"ขนมปัง"
            },
            {
                "level": 2,
                "name":"แซนวิช"
            },
            {
                "level": 2,
                "name":"พาย"
            },
            {
                "level": 2,
                "name":"เดนนิส/ครัวซองค์"
            },
            {
                "level": 2,
                "name":"เค้ก"
            },
            {
                "level": 2,
                "name":"คุ้กกี้"
            },
            {
                "level": 2,
                "name":"ทาร์ต"
            }
        ]
      },
      {
        "id": 11,
        "level": 1,
        "name": "เครื่องดื่ม",
        "children": [
            {
                "level": 2,
                "name":"น้ำดื่ม"
            },
            {
                "level": 2,
                "name":"น้ำผัก และผลไม้"
            },
            {
                "level": 2,
                "name":"เครื่องดื่มเพื่อสุขภาพ"
            },
            {
                "level": 2,
                "name":"ชา"
            },
            {
                "level": 2,
                "name":"กาแฟ"
            },
            {
                "level": 2,
                "name":"เครื่องดื่มอัดก๊าซ/ น้ำอัดลม"
            }
        ]
      },
      {
        "id": 12,
        "level": 1,
        "name": "ผลิตภัณฑ์จากนม",
        "children": [
            {
                "level": 2,
                "name":"นมสด"
            },
            {
                "level": 2,
                "name":"นมเปรี้ยว"
            },
            {
                "level": 2,
                "name":"ครีม"
            },
            {
                "level": 2,
                "name":"ชีส"
            },
            {
                "level": 2,
                "name":"เนย"
            },
            {
                "level": 2,
                "name":"โยเกิร์ต"
            }
        ]
      }
      
    ]
  }
}
